scrapy_jsonrpc/__init__.py
scrapy_jsonrpc/jsonrpc.py
scrapy_jsonrpc/serialize.py
scrapy_jsonrpc/txweb.py
scrapy_jsonrpc/webservice.py
scrapy_jsonrpc_api-1.0.0.dist-info/METADATA
scrapy_jsonrpc_api-1.0.0.dist-info/WHEEL
scrapy_jsonrpc_api-1.0.0.dist-info/top_level.txt
scrapy_jsonrpc_api-1.0.0.dist-info/RECORD
