Metadata-Version: 2.1
Name: scrapy-jsonrpc-api
Version: 1.0.0
Summary: Scrapy extenstion to control spiders using JSON-RPC By Allen
Home-page: https://github.com/xiayus/scrapy-jsonrpc
Author: Scrapy developers,Allen
Author-email: UNKNOWN
License: BSD
Platform: UNKNOWN
Classifier: Framework :: Scrapy
Classifier: Development Status :: 4 - Beta
Classifier: Environment :: Console
Classifier: Intended Audience :: Developers
Classifier: License :: OSI Approved :: BSD License
Classifier: Operating System :: OS Independent
Classifier: Programming Language :: Python
Classifier: Programming Language :: Python :: 2
Classifier: Programming Language :: Python :: 2.7
Classifier: Topic :: Internet :: WWW/HTTP
Requires-Dist: Twisted (>=10.0.0)
Requires-Dist: Scrapy (>=2.4.0)
Requires-Dist: six (>=1.15.0)
Requires-Dist: w3lib (>=1.22.0)
Requires-Dist: urllib3 (>=1.26.2)
